api/main.py
api/request_models.py
api/response_models.py
api/watcher_service.py
sdk/__init__.py
sdk/__main__.py
sdk/orchestration.py
sdk/rendering.py
sdk/utils.py
sdk/watcher.py
sdk/core/exceptions.py
sdk/core/models.py
sdk/core/processing.py
sdk/core/sitemap.py
sdk/core/structuring.py
subtxt-0.1.4.dist-info/METADATA
subtxt-0.1.4.dist-info/WHEEL
subtxt-0.1.4.dist-info/entry_points.txt
subtxt-0.1.4.dist-info/top_level.txt
subtxt-0.1.4.dist-info/RECORD
