Metadata-Version: 2.4
Name: subtxt
Version: 0.1.4
Summary: Generate and auto‑refresh llms.txt for any website using sitemaps.
Author: Ananya Garg
License-Expression: MIT
Requires-Python: >=3.11
Requires-Dist: beautifulsoup4>=4.12
Requires-Dist: lxml>=4.9
Requires-Dist: httpx<0.25,>=0.24
Requires-Dist: pathspec>=0.11
Requires-Dist: ultimate-sitemap-parser>=1.4
Requires-Dist: tqdm>=4.60
Requires-Dist: fastapi>=0.100
Requires-Dist: uvicorn[standard]>=0.20
Requires-Dist: pydantic>=2.0
Requires-Dist: sse-starlette>=1.8.0
